[
	{
		"id": "http://zotero.org/users/180474/items/ZTIB8MAU",
		"type": "chapter",
		"abstract": "We propose a new framework for estimating generative models via an adversarial process, in which we simultaneously train two models:  a generative model G that captures the data distribution, and a discriminative model  D that estimatesthe probability that a sample came from the training data rather than G. The training procedure for G is to maximize the probability of D making a mistake.  This framework corresponds to a minimax two-player game.  In the space of arbitrary functions G and D, a unique solution exists, with G recovering the training data distribution and  D equal to 12 everywhere. In the case where G and D are defined by multilayer perceptrons, the entire system can be trained with backpropagation.There is no need for any Markov chains or unrolled approximate inference networks during either training or generation of samples.  Experiments demonstrate the potential of the framework through qualitative and quantitative evaluation of the generated samples.",
		"container-title": "Advances in Neural Information Processing Systems 27",
		"note": "ZSCC: NoCitationData[s1]",
		"page": "2672–2680",
		"publisher": "Curran Associates, Inc.",
		"source": "Neural Information Processing Systems",
		"title": "Generative Adversarial Nets",
		"URL": "http://papers.nips.cc/paper/5423-generative-adversarial-nets.pdf",
		"author": [
			{
				"family": "Goodfellow",
				"given": "Ian"
			},
			{
				"family": "Pouget-Abadie",
				"given": "Jean"
			},
			{
				"family": "Mirza",
				"given": "Mehdi"
			},
			{
				"family": "Xu",
				"given": "Bing"
			},
			{
				"family": "Warde-Farley",
				"given": "David"
			},
			{
				"family": "Ozair",
				"given": "Sherjil"
			},
			{
				"family": "Courville",
				"given": "Aaron"
			},
			{
				"family": "Bengio",
				"given": "Yoshua"
			}
		],
		"editor": [
			{
				"family": "Ghahramani",
				"given": "Z."
			},
			{
				"family": "Welling",
				"given": "M."
			},
			{
				"family": "Cortes",
				"given": "C."
			},
			{
				"family": "Lawrence",
				"given": "N. D."
			},
			{
				"family": "Weinberger",
				"given": "K. Q."
			}
		],
		"accessed": {
			"date-parts": [
				[
					"2020",
					4,
					4
				]
			]
		},
		"issued": {
			"date-parts": [
				[
					"2014"
				]
			]
		}
	}
]